lasrasterize/__init__.py
lasrasterize/cli.py
lasrasterize/lib.py
lasrasterize/tests/__init__.py
lasrasterize/tests/test_lib.py
lasrasterize/tests/data/sine.las
lasrasterize/tests/data/test.las
lasrasterize-0.2.1.dist-info/entry_points.txt
lasrasterize-0.2.1.dist-info/LICENSE
lasrasterize-0.2.1.dist-info/WHEEL
lasrasterize-0.2.1.dist-info/METADATA
lasrasterize-0.2.1.dist-info/RECORD
